{
  "meta": {
    "generated_by": "build_authors.py",
    "author_count": 293,
    "by_genre": {
      "Science Fiction": 149,
      "Fantasy": 144
    },
    "genres": [
      "Science Fiction",
      "Fantasy"
    ],
    "books_resolution": "each author's books, covers and photo are fetched from openlibrary.org at runtime; each book cross-links to Goodreads"
  },
  "authors": [
    {
      "id": "andre-norton",
      "name": "Andre Norton",
      "genre": "Fantasy",
      "known_for": "Witch World",
      "goodreads_url": "https://www.goodreads.com/search?utf8=%E2%9C%93&q=Andre+Norton&search_type=books&search%5Bfield%5D=author"
    },
    {
      "id": "andrzej-sapkowski",
      "name": "Andrzej Sapkowski",
      "genre": "Fantasy",
      "known_for": "The Witcher",
      "goodreads_url": "https://www.goodreads.com/search?utf8=%E2%9C%93&q=Andrzej+Sapkowski&search_type=books&search%5Bfield%5D=author"
    },
    {
      "id": "anna-smith-spark",
      "name": "Anna Smith Spark",
      "genre": "Fantasy",
      "known_for": "The Court of Broken Knives",
      "goodreads_url": "https://www.goodreads.com/search?utf8=%E2%9C%93&q=Anna+Smith+Spark&search_type=books&search%5Bfield%5D=author"
    },
    {
      "id": "anthony-ryan",
      "name": "Anthony Ryan",
      "genre": "Fantasy",
      "known_for": "Blood Song (Raven's Shadow)",
      "goodreads_url": "https://www.goodreads.com/search?utf8=%E2%9C%93&q=Anthony+Ryan&search_type=books&search%5Bfield%5D=author"
    },
    {
      "id": "barbara-hambly",
      "name": "Barbara Hambly",
      "genre": "Fantasy",
      "known_for": "Dragonsbane",
      "goodreads_url": "https://www.goodreads.com/search?utf8=%E2%9C%93&q=Barbara+Hambly&search_type=books&search%5Bfield%5D=author"
    },
    {
      "id": "brandon-sanderson",
      "name": "Brandon Sanderson",
      "genre": "Fantasy",
      "known_for": "Mistborn; The Stormlight Archive",
      "goodreads_url": "https://www.goodreads.com/search?utf8=%E2%9C%93&q=Brandon+Sanderson&search_type=books&search%5Bfield%5D=author"
    },
    {
      "id": "brent-weeks",
      "name": "Brent Weeks",
      "genre": "Fantasy",
      "known_for": "The Night Angel; Lightbringer",
      "goodreads_url": "https://www.goodreads.com/search?utf8=%E2%9C%93&q=Brent+Weeks&search_type=books&search%5Bfield%5D=author"
    },
    {
      "id": "brian-mcclellan",
      "name": "Brian McClellan",
      "genre": "Fantasy",
      "known_for": "Powder Mage",
      "goodreads_url": "https://www.goodreads.com/search?utf8=%E2%9C%93&q=Brian+McClellan&search_type=books&search%5Bfield%5D=author"
    },
    {
      "id": "brian-staveley",
      "name": "Brian Staveley",
      "genre": "Fantasy",
      "known_for": "The Emperor's Blades",
      "goodreads_url": "https://www.goodreads.com/search?utf8=%E2%9C%93&q=Brian+Staveley&search_type=books&search%5Bfield%5D=author"
    },
    {
      "id": "c-l-moore",
      "name": "C.L. Moore",
      "genre": "Fantasy",
      "known_for": "Jirel of Joiry",
      "goodreads_url": "https://www.goodreads.com/search?utf8=%E2%9C%93&q=C.L.+Moore&search_type=books&search%5Bfield%5D=author"
    },
    {
      "id": "c-s-lewis",
      "name": "C.S. Lewis",
      "genre": "Fantasy",
      "known_for": "The Chronicles of Narnia",
      "goodreads_url": "https://www.goodreads.com/search?utf8=%E2%9C%93&q=C.S.+Lewis&search_type=books&search%5Bfield%5D=author"
    },
    {
      "id": "carol-berg",
      "name": "Carol Berg",
      "genre": "Fantasy",
      "known_for": "Transformation (Rai-kirah)",
      "goodreads_url": "https://www.goodreads.com/search?utf8=%E2%9C%93&q=Carol+Berg&search_type=books&search%5Bfield%5D=author"
    },
    {
      "id": "cassandra-clare",
      "name": "Cassandra Clare",
      "genre": "Fantasy",
      "known_for": "The Mortal Instruments",
      "goodreads_url": "https://www.goodreads.com/search?utf8=%E2%9C%93&q=Cassandra+Clare&search_type=books&search%5Bfield%5D=author"
    },
    {
      "id": "charles-de-lint",
      "name": "Charles de Lint",
      "genre": "Fantasy",
      "known_for": "Newford (urban fantasy)",
      "goodreads_url": "https://www.goodreads.com/search?utf8=%E2%9C%93&q=Charles+de+Lint&search_type=books&search%5Bfield%5D=author"
    },
    {
      "id": "china-mieville",
      "name": "China Miéville",
      "genre": "Fantasy",
      "known_for": "Perdido Street Station (Bas-Lag)",
      "goodreads_url": "https://www.goodreads.com/search?utf8=%E2%9C%93&q=China+Mi%C3%A9ville&search_type=books&search%5Bfield%5D=author"
    },
    {
      "id": "christopher-buehlman",
      "name": "Christopher Buehlman",
      "genre": "Fantasy",
      "known_for": "The Blacktongue Thief",
      "goodreads_url": "https://www.goodreads.com/search?utf8=%E2%9C%93&q=Christopher+Buehlman&search_type=books&search%5Bfield%5D=author"
    },
    {
      "id": "christopher-paolini",
      "name": "Christopher Paolini",
      "genre": "Fantasy",
      "known_for": "The Inheritance Cycle (Eragon)",
      "goodreads_url": "https://www.goodreads.com/search?utf8=%E2%9C%93&q=Christopher+Paolini&search_type=books&search%5Bfield%5D=author"
    },
    {
      "id": "daniel-abraham",
      "name": "Daniel Abraham",
      "genre": "Fantasy",
      "known_for": "The Long Price Quartet; The Dagger and the Coin",
      "goodreads_url": "https://www.goodreads.com/search?utf8=%E2%9C%93&q=Daniel+Abraham&search_type=books&search%5Bfield%5D=author"
    },
    {
      "id": "david-eddings",
      "name": "David Eddings",
      "genre": "Fantasy",
      "known_for": "The Belgariad",
      "goodreads_url": "https://www.goodreads.com/search?utf8=%E2%9C%93&q=David+Eddings&search_type=books&search%5Bfield%5D=author"
    },
    {
      "id": "david-gemmell",
      "name": "David Gemmell",
      "genre": "Fantasy",
      "known_for": "Legend (Drenai)",
      "goodreads_url": "https://www.goodreads.com/search?utf8=%E2%9C%93&q=David+Gemmell&search_type=books&search%5Bfield%5D=author"
    },
    {
      "id": "devin-madson",
      "name": "Devin Madson",
      "genre": "Fantasy",
      "known_for": "We Ride the Storm",
      "goodreads_url": "https://www.goodreads.com/search?utf8=%E2%9C%93&q=Devin+Madson&search_type=books&search%5Bfield%5D=author"
    },
    {
      "id": "diana-wynne-jones",
      "name": "Diana Wynne Jones",
      "genre": "Fantasy",
      "known_for": "Howl's Moving Castle",
      "goodreads_url": "https://www.goodreads.com/search?utf8=%E2%9C%93&q=Diana+Wynne+Jones&search_type=books&search%5Bfield%5D=author"
    },
    {
      "id": "django-wexler",
      "name": "Django Wexler",
      "genre": "Fantasy",
      "known_for": "The Shadow Campaigns",
      "goodreads_url": "https://www.goodreads.com/search?utf8=%E2%9C%93&q=Django+Wexler&search_type=books&search%5Bfield%5D=author"
    },
    {
      "id": "e-r-eddison",
      "name": "E.R. Eddison",
      "genre": "Fantasy",
      "known_for": "The Worm Ouroboros",
      "goodreads_url": "https://www.goodreads.com/search?utf8=%E2%9C%93&q=E.R.+Eddison&search_type=books&search%5Bfield%5D=author"
    },
    {
      "id": "ed-greenwood",
      "name": "Ed Greenwood",
      "genre": "Fantasy",
      "known_for": "The Forgotten Realms (Elminster)",
      "goodreads_url": "https://www.goodreads.com/search?utf8=%E2%9C%93&q=Ed+Greenwood&search_type=books&search%5Bfield%5D=author"
    },
    {
      "id": "ed-mcdonald",
      "name": "Ed McDonald",
      "genre": "Fantasy",
      "known_for": "Blackwing (Raven's Mark)",
      "goodreads_url": "https://www.goodreads.com/search?utf8=%E2%9C%93&q=Ed+McDonald&search_type=books&search%5Bfield%5D=author"
    },
    {
      "id": "elizabeth-haydon",
      "name": "Elizabeth Haydon",
      "genre": "Fantasy",
      "known_for": "The Symphony of Ages (Rhapsody)",
      "goodreads_url": "https://www.goodreads.com/search?utf8=%E2%9C%93&q=Elizabeth+Haydon&search_type=books&search%5Bfield%5D=author"
    },
    {
      "id": "erin-morgenstern",
      "name": "Erin Morgenstern",
      "genre": "Fantasy",
      "known_for": "The Night Circus",
      "goodreads_url": "https://www.goodreads.com/search?utf8=%E2%9C%93&q=Erin+Morgenstern&search_type=books&search%5Bfield%5D=author"
    },
    {
      "id": "evan-winter",
      "name": "Evan Winter",
      "genre": "Fantasy",
      "known_for": "The Rage of Dragons",
      "goodreads_url": "https://www.goodreads.com/search?utf8=%E2%9C%93&q=Evan+Winter&search_type=books&search%5Bfield%5D=author"
    },
    {
      "id": "evangeline-walton",
      "name": "Evangeline Walton",
      "genre": "Fantasy",
      "known_for": "The Mabinogion Tetralogy",
      "goodreads_url": "https://www.goodreads.com/search?utf8=%E2%9C%93&q=Evangeline+Walton&search_type=books&search%5Bfield%5D=author"
    },
    {
      "id": "fiona-mcintosh",
      "name": "Fiona McIntosh",
      "genre": "Fantasy",
      "known_for": "The Quickening",
      "goodreads_url": "https://www.goodreads.com/search?utf8=%E2%9C%93&q=Fiona+McIntosh&search_type=books&search%5Bfield%5D=author"
    },
    {
      "id": "fonda-lee",
      "name": "Fonda Lee",
      "genre": "Fantasy",
      "known_for": "The Green Bone Saga",
      "goodreads_url": "https://www.goodreads.com/search?utf8=%E2%9C%93&q=Fonda+Lee&search_type=books&search%5Bfield%5D=author"
    },
    {
      "id": "fritz-leiber",
      "name": "Fritz Leiber",
      "genre": "Fantasy",
      "known_for": "Fafhrd and the Gray Mouser",
      "goodreads_url": "https://www.goodreads.com/search?utf8=%E2%9C%93&q=Fritz+Leiber&search_type=books&search%5Bfield%5D=author"
    },
    {
      "id": "gail-z-martin",
      "name": "Gail Z. Martin",
      "genre": "Fantasy",
      "known_for": "The Chronicles of the Necromancer",
      "goodreads_url": "https://www.goodreads.com/search?utf8=%E2%9C%93&q=Gail+Z.+Martin&search_type=books&search%5Bfield%5D=author"
    },
    {
      "id": "garth-nix",
      "name": "Garth Nix",
      "genre": "Fantasy",
      "known_for": "Sabriel (The Old Kingdom)",
      "goodreads_url": "https://www.goodreads.com/search?utf8=%E2%9C%93&q=Garth+Nix&search_type=books&search%5Bfield%5D=author"
    },
    {
      "id": "george-macdonald",
      "name": "George MacDonald",
      "genre": "Fantasy",
      "known_for": "Phantastes; The Princess and the Goblin",
      "goodreads_url": "https://www.goodreads.com/search?utf8=%E2%9C%93&q=George+MacDonald&search_type=books&search%5Bfield%5D=author"
    },
    {
      "id": "george-r-r-martin",
      "name": "George R.R. Martin",
      "genre": "Fantasy",
      "known_for": "A Song of Ice and Fire",
      "goodreads_url": "https://www.goodreads.com/search?utf8=%E2%9C%93&q=George+R.R.+Martin&search_type=books&search%5Bfield%5D=author"
    },
    {
      "id": "glen-cook",
      "name": "Glen Cook",
      "genre": "Fantasy",
      "known_for": "The Black Company",
      "goodreads_url": "https://www.goodreads.com/search?utf8=%E2%9C%93&q=Glen+Cook&search_type=books&search%5Bfield%5D=author"
    },
    {
      "id": "guy-gavriel-kay",
      "name": "Guy Gavriel Kay",
      "genre": "Fantasy",
      "known_for": "Tigana; The Lions of Al-Rassan",
      "goodreads_url": "https://www.goodreads.com/search?utf8=%E2%9C%93&q=Guy+Gavriel+Kay&search_type=books&search%5Bfield%5D=author"
    },
    {
      "id": "holly-black",
      "name": "Holly Black",
      "genre": "Fantasy",
      "known_for": "The Folk of the Air (The Cruel Prince)",
      "goodreads_url": "https://www.goodreads.com/search?utf8=%E2%9C%93&q=Holly+Black&search_type=books&search%5Bfield%5D=author"
    },
    {
      "id": "hope-mirrlees",
      "name": "Hope Mirrlees",
      "genre": "Fantasy",
      "known_for": "Lud-in-the-Mist",
      "goodreads_url": "https://www.goodreads.com/search?utf8=%E2%9C%93&q=Hope+Mirrlees&search_type=books&search%5Bfield%5D=author"
    },
    {
      "id": "j-k-rowling",
      "name": "J.K. Rowling",
      "genre": "Fantasy",
      "known_for": "Harry Potter",
      "goodreads_url": "https://www.goodreads.com/search?utf8=%E2%9C%93&q=J.K.+Rowling&search_type=books&search%5Bfield%5D=author"
    },
    {
      "id": "j-r-r-tolkien",
      "name": "J.R.R. Tolkien",
      "genre": "Fantasy",
      "known_for": "The Lord of the Rings; The Hobbit",
      "goodreads_url": "https://www.goodreads.com/search?utf8=%E2%9C%93&q=J.R.R.+Tolkien&search_type=books&search%5Bfield%5D=author"
    },
    {
      "id": "jack-vance",
      "name": "Jack Vance",
      "genre": "Fantasy",
      "known_for": "The Dying Earth; Lyonesse",
      "goodreads_url": "https://www.goodreads.com/search?utf8=%E2%9C%93&q=Jack+Vance&search_type=books&search%5Bfield%5D=author"
    },
    {
      "id": "james-branch-cabell",
      "name": "James Branch Cabell",
      "genre": "Fantasy",
      "known_for": "Jurgen",
      "goodreads_url": "https://www.goodreads.com/search?utf8=%E2%9C%93&q=James+Branch+Cabell&search_type=books&search%5Bfield%5D=author"
    },
    {
      "id": "james-islington",
      "name": "James Islington",
      "genre": "Fantasy",
      "known_for": "The Licanius Trilogy",
      "goodreads_url": "https://www.goodreads.com/search?utf8=%E2%9C%93&q=James+Islington&search_type=books&search%5Bfield%5D=author"
    },
    {
      "id": "janny-wurts",
      "name": "Janny Wurts",
      "genre": "Fantasy",
      "known_for": "The Wars of Light and Shadow",
      "goodreads_url": "https://www.goodreads.com/search?utf8=%E2%9C%93&q=Janny+Wurts&search_type=books&search%5Bfield%5D=author"
    },
    {
      "id": "jen-williams",
      "name": "Jen Williams",
      "genre": "Fantasy",
      "known_for": "The Copper Cat",
      "goodreads_url": "https://www.goodreads.com/search?utf8=%E2%9C%93&q=Jen+Williams&search_type=books&search%5Bfield%5D=author"
    },
    {
      "id": "jenn-lyons",
      "name": "Jenn Lyons",
      "genre": "Fantasy",
      "known_for": "The Ruin of Kings",
      "goodreads_url": "https://www.goodreads.com/search?utf8=%E2%9C%93&q=Jenn+Lyons&search_type=books&search%5Bfield%5D=author"
    },
    {
      "id": "jennifer-l-armentrout",
      "name": "Jennifer L. Armentrout",
      "genre": "Fantasy",
      "known_for": "Blood and Ash",
      "goodreads_url": "https://www.goodreads.com/search?utf8=%E2%9C%93&q=Jennifer+L.+Armentrout&search_type=books&search%5Bfield%5D=author"
    },
    {
      "id": "jim-butcher",
      "name": "Jim Butcher",
      "genre": "Fantasy",
      "known_for": "The Dresden Files",
      "goodreads_url": "https://www.goodreads.com/search?utf8=%E2%9C%93&q=Jim+Butcher&search_type=books&search%5Bfield%5D=author"
    },
    {
      "id": "joe-abercrombie",
      "name": "Joe Abercrombie",
      "genre": "Fantasy",
      "known_for": "The First Law",
      "goodreads_url": "https://www.goodreads.com/search?utf8=%E2%9C%93&q=Joe+Abercrombie&search_type=books&search%5Bfield%5D=author"
    },
    {
      "id": "joe-hill",
      "name": "Joe Hill",
      "genre": "Fantasy",
      "known_for": "NOS4A2",
      "goodreads_url": "https://www.goodreads.com/search?utf8=%E2%9C%93&q=Joe+Hill&search_type=books&search%5Bfield%5D=author"
    },
    {
      "id": "john-gwynne",
      "name": "John Gwynne",
      "genre": "Fantasy",
      "known_for": "The Faithful and the Fallen",
      "goodreads_url": "https://www.goodreads.com/search?utf8=%E2%9C%93&q=John+Gwynne&search_type=books&search%5Bfield%5D=author"
    },
    {
      "id": "john-marco",
      "name": "John Marco",
      "genre": "Fantasy",
      "known_for": "Tyrants and Kings",
      "goodreads_url": "https://www.goodreads.com/search?utf8=%E2%9C%93&q=John+Marco&search_type=books&search%5Bfield%5D=author"
    },
    {
      "id": "jonathan-carroll",
      "name": "Jonathan Carroll",
      "genre": "Fantasy",
      "known_for": "The Land of Laughs",
      "goodreads_url": "https://www.goodreads.com/search?utf8=%E2%9C%93&q=Jonathan+Carroll&search_type=books&search%5Bfield%5D=author"
    },
    {
      "id": "jonathan-stroud",
      "name": "Jonathan Stroud",
      "genre": "Fantasy",
      "known_for": "The Bartimaeus Sequence",
      "goodreads_url": "https://www.goodreads.com/search?utf8=%E2%9C%93&q=Jonathan+Stroud&search_type=books&search%5Bfield%5D=author"
    },
    {
      "id": "josiah-bancroft",
      "name": "Josiah Bancroft",
      "genre": "Fantasy",
      "known_for": "The Books of Babel",
      "goodreads_url": "https://www.goodreads.com/search?utf8=%E2%9C%93&q=Josiah+Bancroft&search_type=books&search%5Bfield%5D=author"
    },
    {
      "id": "juliet-marillier",
      "name": "Juliet Marillier",
      "genre": "Fantasy",
      "known_for": "Sevenwaters",
      "goodreads_url": "https://www.goodreads.com/search?utf8=%E2%9C%93&q=Juliet+Marillier&search_type=books&search%5Bfield%5D=author"
    },
    {
      "id": "karen-miller",
      "name": "Karen Miller",
      "genre": "Fantasy",
      "known_for": "Kingmaker, Kingbreaker",
      "goodreads_url": "https://www.goodreads.com/search?utf8=%E2%9C%93&q=Karen+Miller&search_type=books&search%5Bfield%5D=author"
    },
    {
      "id": "kate-elliott",
      "name": "Kate Elliott",
      "genre": "Fantasy",
      "known_for": "Crown of Stars; Crossroads",
      "goodreads_url": "https://www.goodreads.com/search?utf8=%E2%9C%93&q=Kate+Elliott&search_type=books&search%5Bfield%5D=author"
    },
    {
      "id": "katharine-kerr",
      "name": "Katharine Kerr",
      "genre": "Fantasy",
      "known_for": "Deverry",
      "goodreads_url": "https://www.goodreads.com/search?utf8=%E2%9C%93&q=Katharine+Kerr&search_type=books&search%5Bfield%5D=author"
    },
    {
      "id": "katherine-arden",
      "name": "Katherine Arden",
      "genre": "Fantasy",
      "known_for": "The Winternight Trilogy",
      "goodreads_url": "https://www.goodreads.com/search?utf8=%E2%9C%93&q=Katherine+Arden&search_type=books&search%5Bfield%5D=author"
    },
    {
      "id": "katherine-kurtz",
      "name": "Katherine Kurtz",
      "genre": "Fantasy",
      "known_for": "The Deryni novels",
      "goodreads_url": "https://www.goodreads.com/search?utf8=%E2%9C%93&q=Katherine+Kurtz&search_type=books&search%5Bfield%5D=author"
    },
    {
      "id": "l-sprague-de-camp",
      "name": "L. Sprague de Camp",
      "genre": "Fantasy",
      "known_for": "The Compleat Enchanter",
      "goodreads_url": "https://www.goodreads.com/search?utf8=%E2%9C%93&q=L.+Sprague+de+Camp&search_type=books&search%5Bfield%5D=author"
    },
    {
      "id": "l-e-modesitt-jr",
      "name": "L.E. Modesitt Jr.",
      "genre": "Fantasy",
      "known_for": "The Saga of Recluce",
      "goodreads_url": "https://www.goodreads.com/search?utf8=%E2%9C%93&q=L.E.+Modesitt+Jr.&search_type=books&search%5Bfield%5D=author"
    },
    {
      "id": "leigh-bardugo",
      "name": "Leigh Bardugo",
      "genre": "Fantasy",
      "known_for": "Shadow and Bone; Six of Crows",
      "goodreads_url": "https://www.goodreads.com/search?utf8=%E2%9C%93&q=Leigh+Bardugo&search_type=books&search%5Bfield%5D=author"
    },
    {
      "id": "lev-grossman",
      "name": "Lev Grossman",
      "genre": "Fantasy",
      "known_for": "The Magicians",
      "goodreads_url": "https://www.goodreads.com/search?utf8=%E2%9C%93&q=Lev+Grossman&search_type=books&search%5Bfield%5D=author"
    },
    {
      "id": "lian-hearn",
      "name": "Lian Hearn",
      "genre": "Fantasy",
      "known_for": "Tales of the Otori",
      "goodreads_url": "https://www.goodreads.com/search?utf8=%E2%9C%93&q=Lian+Hearn&search_type=books&search%5Bfield%5D=author"
    },
    {
      "id": "lloyd-alexander",
      "name": "Lloyd Alexander",
      "genre": "Fantasy",
      "known_for": "The Chronicles of Prydain",
      "goodreads_url": "https://www.goodreads.com/search?utf8=%E2%9C%93&q=Lloyd+Alexander&search_type=books&search%5Bfield%5D=author"
    },
    {
      "id": "lord-dunsany",
      "name": "Lord Dunsany",
      "genre": "Fantasy",
      "known_for": "The King of Elfland's Daughter",
      "goodreads_url": "https://www.goodreads.com/search?utf8=%E2%9C%93&q=Lord+Dunsany&search_type=books&search%5Bfield%5D=author"
    },
    {
      "id": "madeline-miller",
      "name": "Madeline Miller",
      "genre": "Fantasy",
      "known_for": "Circe; The Song of Achilles",
      "goodreads_url": "https://www.goodreads.com/search?utf8=%E2%9C%93&q=Madeline+Miller&search_type=books&search%5Bfield%5D=author"
    },
    {
      "id": "maggie-stiefvater",
      "name": "Maggie Stiefvater",
      "genre": "Fantasy",
      "known_for": "The Raven Cycle",
      "goodreads_url": "https://www.goodreads.com/search?utf8=%E2%9C%93&q=Maggie+Stiefvater&search_type=books&search%5Bfield%5D=author"
    },
    {
      "id": "margaret-weis",
      "name": "Margaret Weis",
      "genre": "Fantasy",
      "known_for": "Dragonlance",
      "goodreads_url": "https://www.goodreads.com/search?utf8=%E2%9C%93&q=Margaret+Weis&search_type=books&search%5Bfield%5D=author"
    },
    {
      "id": "marie-lu",
      "name": "Marie Lu",
      "genre": "Fantasy",
      "known_for": "Legend; The Young Elites",
      "goodreads_url": "https://www.goodreads.com/search?utf8=%E2%9C%93&q=Marie+Lu&search_type=books&search%5Bfield%5D=author"
    },
    {
      "id": "mark-lawrence",
      "name": "Mark Lawrence",
      "genre": "Fantasy",
      "known_for": "Prince of Thorns; Red Sister",
      "goodreads_url": "https://www.goodreads.com/search?utf8=%E2%9C%93&q=Mark+Lawrence&search_type=books&search%5Bfield%5D=author"
    },
    {
      "id": "mark-t-barnes",
      "name": "Mark T. Barnes",
      "genre": "Fantasy",
      "known_for": "Echoes of Empire",
      "goodreads_url": "https://www.goodreads.com/search?utf8=%E2%9C%93&q=Mark+T.+Barnes&search_type=books&search%5Bfield%5D=author"
    },
    {
      "id": "max-gladstone",
      "name": "Max Gladstone",
      "genre": "Fantasy",
      "known_for": "The Craft Sequence",
      "goodreads_url": "https://www.goodreads.com/search?utf8=%E2%9C%93&q=Max+Gladstone&search_type=books&search%5Bfield%5D=author"
    },
    {
      "id": "megan-whalen-turner",
      "name": "Megan Whalen Turner",
      "genre": "Fantasy",
      "known_for": "The Queen's Thief (The Thief)",
      "goodreads_url": "https://www.goodreads.com/search?utf8=%E2%9C%93&q=Megan+Whalen+Turner&search_type=books&search%5Bfield%5D=author"
    },
    {
      "id": "mercedes-lackey",
      "name": "Mercedes Lackey",
      "genre": "Fantasy",
      "known_for": "The Heralds of Valdemar",
      "goodreads_url": "https://www.goodreads.com/search?utf8=%E2%9C%93&q=Mercedes+Lackey&search_type=books&search%5Bfield%5D=author"
    },
    {
      "id": "mervyn-peake",
      "name": "Mervyn Peake",
      "genre": "Fantasy",
      "known_for": "Gormenghast",
      "goodreads_url": "https://www.goodreads.com/search?utf8=%E2%9C%93&q=Mervyn+Peake&search_type=books&search%5Bfield%5D=author"
    },
    {
      "id": "michael-j-sullivan",
      "name": "Michael J. Sullivan",
      "genre": "Fantasy",
      "known_for": "The Riyria Revelations",
      "goodreads_url": "https://www.goodreads.com/search?utf8=%E2%9C%93&q=Michael+J.+Sullivan&search_type=books&search%5Bfield%5D=author"
    },
    {
      "id": "michael-moorcock",
      "name": "Michael Moorcock",
      "genre": "Fantasy",
      "known_for": "The Elric Saga",
      "goodreads_url": "https://www.goodreads.com/search?utf8=%E2%9C%93&q=Michael+Moorcock&search_type=books&search%5Bfield%5D=author"
    },
    {
      "id": "miles-cameron",
      "name": "Miles Cameron",
      "genre": "Fantasy",
      "known_for": "The Traitor Son Cycle",
      "goodreads_url": "https://www.goodreads.com/search?utf8=%E2%9C%93&q=Miles+Cameron&search_type=books&search%5Bfield%5D=author"
    },
    {
      "id": "n-k-jemisin",
      "name": "N.K. Jemisin",
      "genre": "Fantasy",
      "known_for": "The Broken Earth",
      "goodreads_url": "https://www.goodreads.com/search?utf8=%E2%9C%93&q=N.K.+Jemisin&search_type=books&search%5Bfield%5D=author"
    },
    {
      "id": "naomi-novik",
      "name": "Naomi Novik",
      "genre": "Fantasy",
      "known_for": "Temeraire; Uprooted",
      "goodreads_url": "https://www.goodreads.com/search?utf8=%E2%9C%93&q=Naomi+Novik&search_type=books&search%5Bfield%5D=author"
    },
    {
      "id": "neil-gaiman",
      "name": "Neil Gaiman",
      "genre": "Fantasy",
      "known_for": "American Gods; The Sandman",
      "goodreads_url": "https://www.goodreads.com/search?utf8=%E2%9C%93&q=Neil+Gaiman&search_type=books&search%5Bfield%5D=author"
    },
    {
      "id": "nghi-vo",
      "name": "Nghi Vo",
      "genre": "Fantasy",
      "known_for": "The Singing Hills Cycle",
      "goodreads_url": "https://www.goodreads.com/search?utf8=%E2%9C%93&q=Nghi+Vo&search_type=books&search%5Bfield%5D=author"
    },
    {
      "id": "nicholas-eames",
      "name": "Nicholas Eames",
      "genre": "Fantasy",
      "known_for": "Kings of the Wyld",
      "goodreads_url": "https://www.goodreads.com/search?utf8=%E2%9C%93&q=Nicholas+Eames&search_type=books&search%5Bfield%5D=author"
    },
    {
      "id": "p-djeli-clark",
      "name": "P. Djèlí Clark",
      "genre": "Fantasy",
      "known_for": "A Master of Djinn",
      "goodreads_url": "https://www.goodreads.com/search?utf8=%E2%9C%93&q=P.+Dj%C3%A8l%C3%AD+Clark&search_type=books&search%5Bfield%5D=author"
    },
    {
      "id": "patricia-a-mckillip",
      "name": "Patricia A. McKillip",
      "genre": "Fantasy",
      "known_for": "The Riddle-Master of Hed",
      "goodreads_url": "https://www.goodreads.com/search?utf8=%E2%9C%93&q=Patricia+A.+McKillip&search_type=books&search%5Bfield%5D=author"
    },
    {
      "id": "patricia-c-wrede",
      "name": "Patricia C. Wrede",
      "genre": "Fantasy",
      "known_for": "Dealing with Dragons",
      "goodreads_url": "https://www.goodreads.com/search?utf8=%E2%9C%93&q=Patricia+C.+Wrede&search_type=books&search%5Bfield%5D=author"
    },
    {
      "id": "patrick-rothfuss",
      "name": "Patrick Rothfuss",
      "genre": "Fantasy",
      "known_for": "The Name of the Wind",
      "goodreads_url": "https://www.goodreads.com/search?utf8=%E2%9C%93&q=Patrick+Rothfuss&search_type=books&search%5Bfield%5D=author"
    },
    {
      "id": "peter-orullian",
      "name": "Peter Orullian",
      "genre": "Fantasy",
      "known_for": "The Vault of Heaven",
      "goodreads_url": "https://www.goodreads.com/search?utf8=%E2%9C%93&q=Peter+Orullian&search_type=books&search%5Bfield%5D=author"
    },
    {
      "id": "peter-s-beagle",
      "name": "Peter S. Beagle",
      "genre": "Fantasy",
      "known_for": "The Last Unicorn",
      "goodreads_url": "https://www.goodreads.com/search?utf8=%E2%9C%93&q=Peter+S.+Beagle&search_type=books&search%5Bfield%5D=author"
    },
    {
      "id": "peter-v-brett",
      "name": "Peter V. Brett",
      "genre": "Fantasy",
      "known_for": "The Demon Cycle",
      "goodreads_url": "https://www.goodreads.com/search?utf8=%E2%9C%93&q=Peter+V.+Brett&search_type=books&search%5Bfield%5D=author"
    },
    {
      "id": "philip-pullman",
      "name": "Philip Pullman",
      "genre": "Fantasy",
      "known_for": "His Dark Materials",
      "goodreads_url": "https://www.goodreads.com/search?utf8=%E2%9C%93&q=Philip+Pullman&search_type=books&search%5Bfield%5D=author"
    },
    {
      "id": "r-scott-bakker",
      "name": "R. Scott Bakker",
      "genre": "Fantasy",
      "known_for": "The Prince of Nothing",
      "goodreads_url": "https://www.goodreads.com/search?utf8=%E2%9C%93&q=R.+Scott+Bakker&search_type=books&search%5Bfield%5D=author"
    },
    {
      "id": "r-a-salvatore",
      "name": "R.A. Salvatore",
      "genre": "Fantasy",
      "known_for": "The Legend of Drizzt",
      "goodreads_url": "https://www.goodreads.com/search?utf8=%E2%9C%93&q=R.A.+Salvatore&search_type=books&search%5Bfield%5D=author"
    },
    {
      "id": "r-f-kuang",
      "name": "R.F. Kuang",
      "genre": "Fantasy",
      "known_for": "The Poppy War; Babel",
      "goodreads_url": "https://www.goodreads.com/search?utf8=%E2%9C%93&q=R.F.+Kuang&search_type=books&search%5Bfield%5D=author"
    },
    {
      "id": "raymond-e-feist",
      "name": "Raymond E. Feist",
      "genre": "Fantasy",
      "known_for": "Magician (The Riftwar Saga)",
      "goodreads_url": "https://www.goodreads.com/search?utf8=%E2%9C%93&q=Raymond+E.+Feist&search_type=books&search%5Bfield%5D=author"
    },
    {
      "id": "rebecca-roanhorse",
      "name": "Rebecca Roanhorse",
      "genre": "Fantasy",
      "known_for": "Trail of Lightning; Black Sun",
      "goodreads_url": "https://www.goodreads.com/search?utf8=%E2%9C%93&q=Rebecca+Roanhorse&search_type=books&search%5Bfield%5D=author"
    },
    {
      "id": "rebecca-yarros",
      "name": "Rebecca Yarros",
      "genre": "Fantasy",
      "known_for": "The Empyrean (Fourth Wing)",
      "goodreads_url": "https://www.goodreads.com/search?utf8=%E2%9C%93&q=Rebecca+Yarros&search_type=books&search%5Bfield%5D=author"
    },
    {
      "id": "rick-riordan",
      "name": "Rick Riordan",
      "genre": "Fantasy",
      "known_for": "Percy Jackson and the Olympians",
      "goodreads_url": "https://www.goodreads.com/search?utf8=%E2%9C%93&q=Rick+Riordan&search_type=books&search%5Bfield%5D=author"
    },
    {
      "id": "robert-e-howard",
      "name": "Robert E. Howard",
      "genre": "Fantasy",
      "known_for": "Conan the Barbarian",
      "goodreads_url": "https://www.goodreads.com/search?utf8=%E2%9C%93&q=Robert+E.+Howard&search_type=books&search%5Bfield%5D=author"
    },
    {
      "id": "robert-jackson-bennett",
      "name": "Robert Jackson Bennett",
      "genre": "Fantasy",
      "known_for": "The Divine Cities; Founders",
      "goodreads_url": "https://www.goodreads.com/search?utf8=%E2%9C%93&q=Robert+Jackson+Bennett&search_type=books&search%5Bfield%5D=author"
    },
    {
      "id": "robert-jordan",
      "name": "Robert Jordan",
      "genre": "Fantasy",
      "known_for": "The Wheel of Time",
      "goodreads_url": "https://www.goodreads.com/search?utf8=%E2%9C%93&q=Robert+Jordan&search_type=books&search%5Bfield%5D=author"
    },
    {
      "id": "robin-hobb",
      "name": "Robin Hobb",
      "genre": "Fantasy",
      "known_for": "The Farseer Trilogy",
      "goodreads_url": "https://www.goodreads.com/search?utf8=%E2%9C%93&q=Robin+Hobb&search_type=books&search%5Bfield%5D=author"
    },
    {
      "id": "robin-mckinley",
      "name": "Robin McKinley",
      "genre": "Fantasy",
      "known_for": "The Blue Sword; Sunshine",
      "goodreads_url": "https://www.goodreads.com/search?utf8=%E2%9C%93&q=Robin+McKinley&search_type=books&search%5Bfield%5D=author"
    },
    {
      "id": "roger-zelazny",
      "name": "Roger Zelazny",
      "genre": "Fantasy",
      "known_for": "The Chronicles of Amber; Lord of Light",
      "goodreads_url": "https://www.goodreads.com/search?utf8=%E2%9C%93&q=Roger+Zelazny&search_type=books&search%5Bfield%5D=author"
    },
    {
      "id": "s-a-chakraborty",
      "name": "S.A. Chakraborty",
      "genre": "Fantasy",
      "known_for": "The Daevabad Trilogy",
      "goodreads_url": "https://www.goodreads.com/search?utf8=%E2%9C%93&q=S.A.+Chakraborty&search_type=books&search%5Bfield%5D=author"
    },
    {
      "id": "sabaa-tahir",
      "name": "Sabaa Tahir",
      "genre": "Fantasy",
      "known_for": "An Ember in the Ashes",
      "goodreads_url": "https://www.goodreads.com/search?utf8=%E2%9C%93&q=Sabaa+Tahir&search_type=books&search%5Bfield%5D=author"
    },
    {
      "id": "sam-sykes",
      "name": "Sam Sykes",
      "genre": "Fantasy",
      "known_for": "Seven Blades in Black",
      "goodreads_url": "https://www.goodreads.com/search?utf8=%E2%9C%93&q=Sam+Sykes&search_type=books&search%5Bfield%5D=author"
    },
    {
      "id": "samantha-shannon",
      "name": "Samantha Shannon",
      "genre": "Fantasy",
      "known_for": "The Priory of the Orange Tree; The Bone Season",
      "goodreads_url": "https://www.goodreads.com/search?utf8=%E2%9C%93&q=Samantha+Shannon&search_type=books&search%5Bfield%5D=author"
    },
    {
      "id": "sarah-beth-durst",
      "name": "Sarah Beth Durst",
      "genre": "Fantasy",
      "known_for": "The Queens of Renthia",
      "goodreads_url": "https://www.goodreads.com/search?utf8=%E2%9C%93&q=Sarah+Beth+Durst&search_type=books&search%5Bfield%5D=author"
    },
    {
      "id": "sarah-j-maas",
      "name": "Sarah J. Maas",
      "genre": "Fantasy",
      "known_for": "Throne of Glass; A Court of Thorns and Roses",
      "goodreads_url": "https://www.goodreads.com/search?utf8=%E2%9C%93&q=Sarah+J.+Maas&search_type=books&search%5Bfield%5D=author"
    },
    {
      "id": "scott-lynch",
      "name": "Scott Lynch",
      "genre": "Fantasy",
      "known_for": "The Lies of Locke Lamora",
      "goodreads_url": "https://www.goodreads.com/search?utf8=%E2%9C%93&q=Scott+Lynch&search_type=books&search%5Bfield%5D=author"
    },
    {
      "id": "sebastien-de-castell",
      "name": "Sebastien de Castell",
      "genre": "Fantasy",
      "known_for": "Greatcoats",
      "goodreads_url": "https://www.goodreads.com/search?utf8=%E2%9C%93&q=Sebastien+de+Castell&search_type=books&search%5Bfield%5D=author"
    },
    {
      "id": "seth-dickinson",
      "name": "Seth Dickinson",
      "genre": "Fantasy",
      "known_for": "The Traitor Baru Cormorant",
      "goodreads_url": "https://www.goodreads.com/search?utf8=%E2%9C%93&q=Seth+Dickinson&search_type=books&search%5Bfield%5D=author"
    },
    {
      "id": "stephen-deas",
      "name": "Stephen Deas",
      "genre": "Fantasy",
      "known_for": "The Adar (Memory of Flames)",
      "goodreads_url": "https://www.goodreads.com/search?utf8=%E2%9C%93&q=Stephen+Deas&search_type=books&search%5Bfield%5D=author"
    },
    {
      "id": "stephen-king",
      "name": "Stephen King",
      "genre": "Fantasy",
      "known_for": "The Dark Tower",
      "goodreads_url": "https://www.goodreads.com/search?utf8=%E2%9C%93&q=Stephen+King&search_type=books&search%5Bfield%5D=author"
    },
    {
      "id": "stephen-r-donaldson",
      "name": "Stephen R. Donaldson",
      "genre": "Fantasy",
      "known_for": "The Chronicles of Thomas Covenant",
      "goodreads_url": "https://www.goodreads.com/search?utf8=%E2%9C%93&q=Stephen+R.+Donaldson&search_type=books&search%5Bfield%5D=author"
    },
    {
      "id": "steven-brust",
      "name": "Steven Brust",
      "genre": "Fantasy",
      "known_for": "Vlad Taltos",
      "goodreads_url": "https://www.goodreads.com/search?utf8=%E2%9C%93&q=Steven+Brust&search_type=books&search%5Bfield%5D=author"
    },
    {
      "id": "steven-erikson",
      "name": "Steven Erikson",
      "genre": "Fantasy",
      "known_for": "Malazan Book of the Fallen",
      "goodreads_url": "https://www.goodreads.com/search?utf8=%E2%9C%93&q=Steven+Erikson&search_type=books&search%5Bfield%5D=author"
    },
    {
      "id": "susan-cooper",
      "name": "Susan Cooper",
      "genre": "Fantasy",
      "known_for": "The Dark Is Rising",
      "goodreads_url": "https://www.goodreads.com/search?utf8=%E2%9C%93&q=Susan+Cooper&search_type=books&search%5Bfield%5D=author"
    },
    {
      "id": "susanna-clarke",
      "name": "Susanna Clarke",
      "genre": "Fantasy",
      "known_for": "Jonathan Strange & Mr Norrell; Piranesi",
      "goodreads_url": "https://www.goodreads.com/search?utf8=%E2%9C%93&q=Susanna+Clarke&search_type=books&search%5Bfield%5D=author"
    },
    {
      "id": "t-kingfisher",
      "name": "T. Kingfisher",
      "genre": "Fantasy",
      "known_for": "Nettle & Bone",
      "goodreads_url": "https://www.goodreads.com/search?utf8=%E2%9C%93&q=T.+Kingfisher&search_type=books&search%5Bfield%5D=author"
    },
    {
      "id": "t-h-white",
      "name": "T.H. White",
      "genre": "Fantasy",
      "known_for": "The Once and Future King",
      "goodreads_url": "https://www.goodreads.com/search?utf8=%E2%9C%93&q=T.H.+White&search_type=books&search%5Bfield%5D=author"
    },
    {
      "id": "tad-williams",
      "name": "Tad Williams",
      "genre": "Fantasy",
      "known_for": "Memory, Sorrow, and Thorn",
      "goodreads_url": "https://www.goodreads.com/search?utf8=%E2%9C%93&q=Tad+Williams&search_type=books&search%5Bfield%5D=author"
    },
    {
      "id": "tamora-pierce",
      "name": "Tamora Pierce",
      "genre": "Fantasy",
      "known_for": "Song of the Lioness",
      "goodreads_url": "https://www.goodreads.com/search?utf8=%E2%9C%93&q=Tamora+Pierce&search_type=books&search%5Bfield%5D=author"
    },
    {
      "id": "tanith-lee",
      "name": "Tanith Lee",
      "genre": "Fantasy",
      "known_for": "The Flat Earth (Tales)",
      "goodreads_url": "https://www.goodreads.com/search?utf8=%E2%9C%93&q=Tanith+Lee&search_type=books&search%5Bfield%5D=author"
    },
    {
      "id": "tasha-suri",
      "name": "Tasha Suri",
      "genre": "Fantasy",
      "known_for": "The Jasmine Throne",
      "goodreads_url": "https://www.goodreads.com/search?utf8=%E2%9C%93&q=Tasha+Suri&search_type=books&search%5Bfield%5D=author"
    },
    {
      "id": "terry-brooks",
      "name": "Terry Brooks",
      "genre": "Fantasy",
      "known_for": "Shannara",
      "goodreads_url": "https://www.goodreads.com/search?utf8=%E2%9C%93&q=Terry+Brooks&search_type=books&search%5Bfield%5D=author"
    },
    {
      "id": "terry-goodkind",
      "name": "Terry Goodkind",
      "genre": "Fantasy",
      "known_for": "The Sword of Truth",
      "goodreads_url": "https://www.goodreads.com/search?utf8=%E2%9C%93&q=Terry+Goodkind&search_type=books&search%5Bfield%5D=author"
    },
    {
      "id": "terry-pratchett",
      "name": "Terry Pratchett",
      "genre": "Fantasy",
      "known_for": "Discworld",
      "goodreads_url": "https://www.goodreads.com/search?utf8=%E2%9C%93&q=Terry+Pratchett&search_type=books&search%5Bfield%5D=author"
    },
    {
      "id": "tim-powers",
      "name": "Tim Powers",
      "genre": "Fantasy",
      "known_for": "The Anubis Gates; Last Call",
      "goodreads_url": "https://www.goodreads.com/search?utf8=%E2%9C%93&q=Tim+Powers&search_type=books&search%5Bfield%5D=author"
    },
    {
      "id": "tomi-adeyemi",
      "name": "Tomi Adeyemi",
      "genre": "Fantasy",
      "known_for": "Children of Blood and Bone",
      "goodreads_url": "https://www.goodreads.com/search?utf8=%E2%9C%93&q=Tomi+Adeyemi&search_type=books&search%5Bfield%5D=author"
    },
    {
      "id": "tracy-hickman",
      "name": "Tracy Hickman",
      "genre": "Fantasy",
      "known_for": "Dragonlance",
      "goodreads_url": "https://www.goodreads.com/search?utf8=%E2%9C%93&q=Tracy+Hickman&search_type=books&search%5Bfield%5D=author"
    },
    {
      "id": "travis-baldree",
      "name": "Travis Baldree",
      "genre": "Fantasy",
      "known_for": "Legends & Lattes",
      "goodreads_url": "https://www.goodreads.com/search?utf8=%E2%9C%93&q=Travis+Baldree&search_type=books&search%5Bfield%5D=author"
    },
    {
      "id": "trudi-canavan",
      "name": "Trudi Canavan",
      "genre": "Fantasy",
      "known_for": "The Black Magician Trilogy",
      "goodreads_url": "https://www.goodreads.com/search?utf8=%E2%9C%93&q=Trudi+Canavan&search_type=books&search%5Bfield%5D=author"
    },
    {
      "id": "ursula-vernon",
      "name": "Ursula Vernon",
      "genre": "Fantasy",
      "known_for": "Digger",
      "goodreads_url": "https://www.goodreads.com/search?utf8=%E2%9C%93&q=Ursula+Vernon&search_type=books&search%5Bfield%5D=author"
    },
    {
      "id": "v-e-schwab",
      "name": "V.E. Schwab",
      "genre": "Fantasy",
      "known_for": "A Darker Shade of Magic",
      "goodreads_url": "https://www.goodreads.com/search?utf8=%E2%9C%93&q=V.E.+Schwab&search_type=books&search%5Bfield%5D=author"
    },
    {
      "id": "will-wight",
      "name": "Will Wight",
      "genre": "Fantasy",
      "known_for": "Cradle",
      "goodreads_url": "https://www.goodreads.com/search?utf8=%E2%9C%93&q=Will+Wight&search_type=books&search%5Bfield%5D=author"
    },
    {
      "id": "william-morris",
      "name": "William Morris",
      "genre": "Fantasy",
      "known_for": "The Well at the World's End",
      "goodreads_url": "https://www.goodreads.com/search?utf8=%E2%9C%93&q=William+Morris&search_type=books&search%5Bfield%5D=author"
    },
    {
      "id": "a-e-van-vogt",
      "name": "A.E. van Vogt",
      "genre": "Science Fiction",
      "known_for": "Slan; The Voyage of the Space Beagle",
      "goodreads_url": "https://www.goodreads.com/search?utf8=%E2%9C%93&q=A.E.+van+Vogt&search_type=books&search%5Bfield%5D=author"
    },
    {
      "id": "ada-palmer",
      "name": "Ada Palmer",
      "genre": "Science Fiction",
      "known_for": "Too Like the Lightning",
      "goodreads_url": "https://www.goodreads.com/search?utf8=%E2%9C%93&q=Ada+Palmer&search_type=books&search%5Bfield%5D=author"
    },
    {
      "id": "adam-roberts",
      "name": "Adam Roberts",
      "genre": "Science Fiction",
      "known_for": "Jack Glass",
      "goodreads_url": "https://www.goodreads.com/search?utf8=%E2%9C%93&q=Adam+Roberts&search_type=books&search%5Bfield%5D=author"
    },
    {
      "id": "adrian-tchaikovsky",
      "name": "Adrian Tchaikovsky",
      "genre": "Science Fiction",
      "known_for": "Children of Time",
      "goodreads_url": "https://www.goodreads.com/search?utf8=%E2%9C%93&q=Adrian+Tchaikovsky&search_type=books&search%5Bfield%5D=author"
    },
    {
      "id": "alastair-reynolds",
      "name": "Alastair Reynolds",
      "genre": "Science Fiction",
      "known_for": "Revelation Space",
      "goodreads_url": "https://www.goodreads.com/search?utf8=%E2%9C%93&q=Alastair+Reynolds&search_type=books&search%5Bfield%5D=author"
    },
    {
      "id": "alfred-bester",
      "name": "Alfred Bester",
      "genre": "Science Fiction",
      "known_for": "The Stars My Destination; The Demolished Man",
      "goodreads_url": "https://www.goodreads.com/search?utf8=%E2%9C%93&q=Alfred+Bester&search_type=books&search%5Bfield%5D=author"
    },
    {
      "id": "aliette-de-bodard",
      "name": "Aliette de Bodard",
      "genre": "Science Fiction",
      "known_for": "The Tea Master and the Detective",
      "goodreads_url": "https://www.goodreads.com/search?utf8=%E2%9C%93&q=Aliette+de+Bodard&search_type=books&search%5Bfield%5D=author"
    },
    {
      "id": "andy-weir",
      "name": "Andy Weir",
      "genre": "Science Fiction",
      "known_for": "The Martian; Project Hail Mary",
      "goodreads_url": "https://www.goodreads.com/search?utf8=%E2%9C%93&q=Andy+Weir&search_type=books&search%5Bfield%5D=author"
    },
    {
      "id": "ann-leckie",
      "name": "Ann Leckie",
      "genre": "Science Fiction",
      "known_for": "Ancillary Justice",
      "goodreads_url": "https://www.goodreads.com/search?utf8=%E2%9C%93&q=Ann+Leckie&search_type=books&search%5Bfield%5D=author"
    },
    {
      "id": "annalee-newitz",
      "name": "Annalee Newitz",
      "genre": "Science Fiction",
      "known_for": "Autonomous",
      "goodreads_url": "https://www.goodreads.com/search?utf8=%E2%9C%93&q=Annalee+Newitz&search_type=books&search%5Bfield%5D=author"
    },
    {
      "id": "anne-mccaffrey",
      "name": "Anne McCaffrey",
      "genre": "Science Fiction",
      "known_for": "Dragonriders of Pern",
      "goodreads_url": "https://www.goodreads.com/search?utf8=%E2%9C%93&q=Anne+McCaffrey&search_type=books&search%5Bfield%5D=author"
    },
    {
      "id": "arkady-martine",
      "name": "Arkady Martine",
      "genre": "Science Fiction",
      "known_for": "A Memory Called Empire",
      "goodreads_url": "https://www.goodreads.com/search?utf8=%E2%9C%93&q=Arkady+Martine&search_type=books&search%5Bfield%5D=author"
    },
    {
      "id": "arthur-c-clarke",
      "name": "Arthur C. Clarke",
      "genre": "Science Fiction",
      "known_for": "2001: A Space Odyssey; Rendezvous with Rama",
      "goodreads_url": "https://www.goodreads.com/search?utf8=%E2%9C%93&q=Arthur+C.+Clarke&search_type=books&search%5Bfield%5D=author"
    },
    {
      "id": "becky-chambers",
      "name": "Becky Chambers",
      "genre": "Science Fiction",
      "known_for": "The Long Way to a Small, Angry Planet",
      "goodreads_url": "https://www.goodreads.com/search?utf8=%E2%9C%93&q=Becky+Chambers&search_type=books&search%5Bfield%5D=author"
    },
    {
      "id": "blake-crouch",
      "name": "Blake Crouch",
      "genre": "Science Fiction",
      "known_for": "Dark Matter; Recursion",
      "goodreads_url": "https://www.goodreads.com/search?utf8=%E2%9C%93&q=Blake+Crouch&search_type=books&search%5Bfield%5D=author"
    },
    {
      "id": "brian-aldiss",
      "name": "Brian Aldiss",
      "genre": "Science Fiction",
      "known_for": "Helliconia; Non-Stop",
      "goodreads_url": "https://www.goodreads.com/search?utf8=%E2%9C%93&q=Brian+Aldiss&search_type=books&search%5Bfield%5D=author"
    },
    {
      "id": "bruce-sterling",
      "name": "Bruce Sterling",
      "genre": "Science Fiction",
      "known_for": "Schismatrix; Islands in the Net",
      "goodreads_url": "https://www.goodreads.com/search?utf8=%E2%9C%93&q=Bruce+Sterling&search_type=books&search%5Bfield%5D=author"
    },
    {
      "id": "c-j-cherryh",
      "name": "C.J. Cherryh",
      "genre": "Science Fiction",
      "known_for": "Downbelow Station; Cyteen",
      "goodreads_url": "https://www.goodreads.com/search?utf8=%E2%9C%93&q=C.J.+Cherryh&search_type=books&search%5Bfield%5D=author"
    },
    {
      "id": "charles-sheffield",
      "name": "Charles Sheffield",
      "genre": "Science Fiction",
      "known_for": "The McAndrew Chronicles",
      "goodreads_url": "https://www.goodreads.com/search?utf8=%E2%9C%93&q=Charles+Sheffield&search_type=books&search%5Bfield%5D=author"
    },
    {
      "id": "charles-stross",
      "name": "Charles Stross",
      "genre": "Science Fiction",
      "known_for": "Accelerando",
      "goodreads_url": "https://www.goodreads.com/search?utf8=%E2%9C%93&q=Charles+Stross&search_type=books&search%5Bfield%5D=author"
    },
    {
      "id": "charlie-jane-anders",
      "name": "Charlie Jane Anders",
      "genre": "Science Fiction",
      "known_for": "All the Birds in the Sky",
      "goodreads_url": "https://www.goodreads.com/search?utf8=%E2%9C%93&q=Charlie+Jane+Anders&search_type=books&search%5Bfield%5D=author"
    },
    {
      "id": "christopher-priest",
      "name": "Christopher Priest",
      "genre": "Science Fiction",
      "known_for": "The Prestige; Inverted World",
      "goodreads_url": "https://www.goodreads.com/search?utf8=%E2%9C%93&q=Christopher+Priest&search_type=books&search%5Bfield%5D=author"
    },
    {
      "id": "clifford-d-simak",
      "name": "Clifford D. Simak",
      "genre": "Science Fiction",
      "known_for": "City; Way Station",
      "goodreads_url": "https://www.goodreads.com/search?utf8=%E2%9C%93&q=Clifford+D.+Simak&search_type=books&search%5Bfield%5D=author"
    },
    {
      "id": "connie-willis",
      "name": "Connie Willis",
      "genre": "Science Fiction",
      "known_for": "Doomsday Book; To Say Nothing of the Dog",
      "goodreads_url": "https://www.goodreads.com/search?utf8=%E2%9C%93&q=Connie+Willis&search_type=books&search%5Bfield%5D=author"
    },
    {
      "id": "cordwainer-smith",
      "name": "Cordwainer Smith",
      "genre": "Science Fiction",
      "known_for": "The Instrumentality of Mankind",
      "goodreads_url": "https://www.goodreads.com/search?utf8=%E2%9C%93&q=Cordwainer+Smith&search_type=books&search%5Bfield%5D=author"
    },
    {
      "id": "cory-doctorow",
      "name": "Cory Doctorow",
      "genre": "Science Fiction",
      "known_for": "Little Brother",
      "goodreads_url": "https://www.goodreads.com/search?utf8=%E2%9C%93&q=Cory+Doctorow&search_type=books&search%5Bfield%5D=author"
    },
    {
      "id": "cyril-m-kornbluth",
      "name": "Cyril M. Kornbluth",
      "genre": "Science Fiction",
      "known_for": "The Space Merchants (with Pohl)",
      "goodreads_url": "https://www.goodreads.com/search?utf8=%E2%9C%93&q=Cyril+M.+Kornbluth&search_type=books&search%5Bfield%5D=author"
    },
    {
      "id": "damon-knight",
      "name": "Damon Knight",
      "genre": "Science Fiction",
      "known_for": "CV; To Serve Man",
      "goodreads_url": "https://www.goodreads.com/search?utf8=%E2%9C%93&q=Damon+Knight&search_type=books&search%5Bfield%5D=author"
    },
    {
      "id": "dan-simmons",
      "name": "Dan Simmons",
      "genre": "Science Fiction",
      "known_for": "Hyperion",
      "goodreads_url": "https://www.goodreads.com/search?utf8=%E2%9C%93&q=Dan+Simmons&search_type=books&search%5Bfield%5D=author"
    },
    {
      "id": "daniel-suarez",
      "name": "Daniel Suarez",
      "genre": "Science Fiction",
      "known_for": "Daemon",
      "goodreads_url": "https://www.goodreads.com/search?utf8=%E2%9C%93&q=Daniel+Suarez&search_type=books&search%5Bfield%5D=author"
    },
    {
      "id": "david-brin",
      "name": "David Brin",
      "genre": "Science Fiction",
      "known_for": "The Uplift War; Startide Rising",
      "goodreads_url": "https://www.goodreads.com/search?utf8=%E2%9C%93&q=David+Brin&search_type=books&search%5Bfield%5D=author"
    },
    {
      "id": "david-drake",
      "name": "David Drake",
      "genre": "Science Fiction",
      "known_for": "Hammer's Slammers",
      "goodreads_url": "https://www.goodreads.com/search?utf8=%E2%9C%93&q=David+Drake&search_type=books&search%5Bfield%5D=author"
    },
    {
      "id": "david-marusek",
      "name": "David Marusek",
      "genre": "Science Fiction",
      "known_for": "Counting Heads",
      "goodreads_url": "https://www.goodreads.com/search?utf8=%E2%9C%93&q=David+Marusek&search_type=books&search%5Bfield%5D=author"
    },
    {
      "id": "david-weber",
      "name": "David Weber",
      "genre": "Science Fiction",
      "known_for": "Honor Harrington",
      "goodreads_url": "https://www.goodreads.com/search?utf8=%E2%9C%93&q=David+Weber&search_type=books&search%5Bfield%5D=author"
    },
    {
      "id": "dennis-e-taylor",
      "name": "Dennis E. Taylor",
      "genre": "Science Fiction",
      "known_for": "We Are Legion (We Are Bob)",
      "goodreads_url": "https://www.goodreads.com/search?utf8=%E2%9C%93&q=Dennis+E.+Taylor&search_type=books&search%5Bfield%5D=author"
    },
    {
      "id": "e-e-doc-smith",
      "name": "E.E. \"Doc\" Smith",
      "genre": "Science Fiction",
      "known_for": "Lensman; Skylark",
      "goodreads_url": "https://www.goodreads.com/search?utf8=%E2%9C%93&q=E.E.+%22Doc%22+Smith&search_type=books&search%5Bfield%5D=author"
    },
    {
      "id": "edmond-hamilton",
      "name": "Edmond Hamilton",
      "genre": "Science Fiction",
      "known_for": "The Star Kings; Captain Future",
      "goodreads_url": "https://www.goodreads.com/search?utf8=%E2%9C%93&q=Edmond+Hamilton&search_type=books&search%5Bfield%5D=author"
    },
    {
      "id": "elizabeth-moon",
      "name": "Elizabeth Moon",
      "genre": "Science Fiction",
      "known_for": "The Speed of Dark; Vatta's War",
      "goodreads_url": "https://www.goodreads.com/search?utf8=%E2%9C%93&q=Elizabeth+Moon&search_type=books&search%5Bfield%5D=author"
    },
    {
      "id": "emily-st-john-mandel",
      "name": "Emily St. John Mandel",
      "genre": "Science Fiction",
      "known_for": "Station Eleven",
      "goodreads_url": "https://www.goodreads.com/search?utf8=%E2%9C%93&q=Emily+St.+John+Mandel&search_type=books&search%5Bfield%5D=author"
    },
    {
      "id": "eric-flint",
      "name": "Eric Flint",
      "genre": "Science Fiction",
      "known_for": "1632",
      "goodreads_url": "https://www.goodreads.com/search?utf8=%E2%9C%93&q=Eric+Flint&search_type=books&search%5Bfield%5D=author"
    },
    {
      "id": "ernest-cline",
      "name": "Ernest Cline",
      "genre": "Science Fiction",
      "known_for": "Ready Player One",
      "goodreads_url": "https://www.goodreads.com/search?utf8=%E2%9C%93&q=Ernest+Cline&search_type=books&search%5Bfield%5D=author"
    },
    {
      "id": "frank-herbert",
      "name": "Frank Herbert",
      "genre": "Science Fiction",
      "known_for": "Dune",
      "goodreads_url": "https://www.goodreads.com/search?utf8=%E2%9C%93&q=Frank+Herbert&search_type=books&search%5Bfield%5D=author"
    },
    {
      "id": "fred-saberhagen",
      "name": "Fred Saberhagen",
      "genre": "Science Fiction",
      "known_for": "Berserker",
      "goodreads_url": "https://www.goodreads.com/search?utf8=%E2%9C%93&q=Fred+Saberhagen&search_type=books&search%5Bfield%5D=author"
    },
    {
      "id": "frederik-pohl",
      "name": "Frederik Pohl",
      "genre": "Science Fiction",
      "known_for": "Gateway; The Space Merchants",
      "goodreads_url": "https://www.goodreads.com/search?utf8=%E2%9C%93&q=Frederik+Pohl&search_type=books&search%5Bfield%5D=author"
    },
    {
      "id": "gareth-l-powell",
      "name": "Gareth L. Powell",
      "genre": "Science Fiction",
      "known_for": "Embers of War",
      "goodreads_url": "https://www.goodreads.com/search?utf8=%E2%9C%93&q=Gareth+L.+Powell&search_type=books&search%5Bfield%5D=author"
    },
    {
      "id": "gene-wolfe",
      "name": "Gene Wolfe",
      "genre": "Science Fiction",
      "known_for": "The Book of the New Sun",
      "goodreads_url": "https://www.goodreads.com/search?utf8=%E2%9C%93&q=Gene+Wolfe&search_type=books&search%5Bfield%5D=author"
    },
    {
      "id": "greg-bear",
      "name": "Greg Bear",
      "genre": "Science Fiction",
      "known_for": "Blood Music; Eon",
      "goodreads_url": "https://www.goodreads.com/search?utf8=%E2%9C%93&q=Greg+Bear&search_type=books&search%5Bfield%5D=author"
    },
    {
      "id": "greg-egan",
      "name": "Greg Egan",
      "genre": "Science Fiction",
      "known_for": "Permutation City; Diaspora",
      "goodreads_url": "https://www.goodreads.com/search?utf8=%E2%9C%93&q=Greg+Egan&search_type=books&search%5Bfield%5D=author"
    },
    {
      "id": "gregory-benford",
      "name": "Gregory Benford",
      "genre": "Science Fiction",
      "known_for": "Timescape",
      "goodreads_url": "https://www.goodreads.com/search?utf8=%E2%9C%93&q=Gregory+Benford&search_type=books&search%5Bfield%5D=author"
    },
    {
      "id": "gwyneth-jones",
      "name": "Gwyneth Jones",
      "genre": "Science Fiction",
      "known_for": "Bold as Love",
      "goodreads_url": "https://www.goodreads.com/search?utf8=%E2%9C%93&q=Gwyneth+Jones&search_type=books&search%5Bfield%5D=author"
    },
    {
      "id": "h-g-wells",
      "name": "H.G. Wells",
      "genre": "Science Fiction",
      "known_for": "The Time Machine; The War of the Worlds",
      "goodreads_url": "https://www.goodreads.com/search?utf8=%E2%9C%93&q=H.G.+Wells&search_type=books&search%5Bfield%5D=author"
    },
    {
      "id": "hal-clement",
      "name": "Hal Clement",
      "genre": "Science Fiction",
      "known_for": "Mission of Gravity",
      "goodreads_url": "https://www.goodreads.com/search?utf8=%E2%9C%93&q=Hal+Clement&search_type=books&search%5Bfield%5D=author"
    },
    {
      "id": "hannu-rajaniemi",
      "name": "Hannu Rajaniemi",
      "genre": "Science Fiction",
      "known_for": "The Quantum Thief",
      "goodreads_url": "https://www.goodreads.com/search?utf8=%E2%9C%93&q=Hannu+Rajaniemi&search_type=books&search%5Bfield%5D=author"
    },
    {
      "id": "harlan-ellison",
      "name": "Harlan Ellison",
      "genre": "Science Fiction",
      "known_for": "I Have No Mouth, and I Must Scream",
      "goodreads_url": "https://www.goodreads.com/search?utf8=%E2%9C%93&q=Harlan+Ellison&search_type=books&search%5Bfield%5D=author"
    },
    {
      "id": "harry-harrison",
      "name": "Harry Harrison",
      "genre": "Science Fiction",
      "known_for": "The Stainless Steel Rat; Make Room! Make Room!",
      "goodreads_url": "https://www.goodreads.com/search?utf8=%E2%9C%93&q=Harry+Harrison&search_type=books&search%5Bfield%5D=author"
    },
    {
      "id": "harry-turtledove",
      "name": "Harry Turtledove",
      "genre": "Science Fiction",
      "known_for": "The Guns of the South; Worldwar",
      "goodreads_url": "https://www.goodreads.com/search?utf8=%E2%9C%93&q=Harry+Turtledove&search_type=books&search%5Bfield%5D=author"
    },
    {
      "id": "hugh-howey",
      "name": "Hugh Howey",
      "genre": "Science Fiction",
      "known_for": "Wool (Silo)",
      "goodreads_url": "https://www.goodreads.com/search?utf8=%E2%9C%93&q=Hugh+Howey&search_type=books&search%5Bfield%5D=author"
    },
    {
      "id": "iain-m-banks",
      "name": "Iain M. Banks",
      "genre": "Science Fiction",
      "known_for": "The Culture novels",
      "goodreads_url": "https://www.goodreads.com/search?utf8=%E2%9C%93&q=Iain+M.+Banks&search_type=books&search%5Bfield%5D=author"
    },
    {
      "id": "isaac-asimov",
      "name": "Isaac Asimov",
      "genre": "Science Fiction",
      "known_for": "Foundation; I, Robot",
      "goodreads_url": "https://www.goodreads.com/search?utf8=%E2%9C%93&q=Isaac+Asimov&search_type=books&search%5Bfield%5D=author"
    },
    {
      "id": "j-g-ballard",
      "name": "J.G. Ballard",
      "genre": "Science Fiction",
      "known_for": "The Drowned World; Crash",
      "goodreads_url": "https://www.goodreads.com/search?utf8=%E2%9C%93&q=J.G.+Ballard&search_type=books&search%5Bfield%5D=author"
    },
    {
      "id": "jack-campbell",
      "name": "Jack Campbell",
      "genre": "Science Fiction",
      "known_for": "The Lost Fleet",
      "goodreads_url": "https://www.goodreads.com/search?utf8=%E2%9C%93&q=Jack+Campbell&search_type=books&search%5Bfield%5D=author"
    },
    {
      "id": "jack-mcdevitt",
      "name": "Jack McDevitt",
      "genre": "Science Fiction",
      "known_for": "The Engines of God",
      "goodreads_url": "https://www.goodreads.com/search?utf8=%E2%9C%93&q=Jack+McDevitt&search_type=books&search%5Bfield%5D=author"
    },
    {
      "id": "jack-williamson",
      "name": "Jack Williamson",
      "genre": "Science Fiction",
      "known_for": "The Humanoids; Legion of Space",
      "goodreads_url": "https://www.goodreads.com/search?utf8=%E2%9C%93&q=Jack+Williamson&search_type=books&search%5Bfield%5D=author"
    },
    {
      "id": "james-blish",
      "name": "James Blish",
      "genre": "Science Fiction",
      "known_for": "A Case of Conscience; Cities in Flight",
      "goodreads_url": "https://www.goodreads.com/search?utf8=%E2%9C%93&q=James+Blish&search_type=books&search%5Bfield%5D=author"
    },
    {
      "id": "james-p-hogan",
      "name": "James P. Hogan",
      "genre": "Science Fiction",
      "known_for": "Inherit the Stars",
      "goodreads_url": "https://www.goodreads.com/search?utf8=%E2%9C%93&q=James+P.+Hogan&search_type=books&search%5Bfield%5D=author"
    },
    {
      "id": "james-s-a-corey",
      "name": "James S.A. Corey",
      "genre": "Science Fiction",
      "known_for": "The Expanse",
      "goodreads_url": "https://www.goodreads.com/search?utf8=%E2%9C%93&q=James+S.A.+Corey&search_type=books&search%5Bfield%5D=author"
    },
    {
      "id": "james-tiptree-jr",
      "name": "James Tiptree Jr.",
      "genre": "Science Fiction",
      "known_for": "Her Smoke Rose Up Forever",
      "goodreads_url": "https://www.goodreads.com/search?utf8=%E2%9C%93&q=James+Tiptree+Jr.&search_type=books&search%5Bfield%5D=author"
    },
    {
      "id": "jeff-vandermeer",
      "name": "Jeff VanderMeer",
      "genre": "Science Fiction",
      "known_for": "Annihilation (Southern Reach)",
      "goodreads_url": "https://www.goodreads.com/search?utf8=%E2%9C%93&q=Jeff+VanderMeer&search_type=books&search%5Bfield%5D=author"
    },
    {
      "id": "jerry-pournelle",
      "name": "Jerry Pournelle",
      "genre": "Science Fiction",
      "known_for": "The Mote in God's Eye",
      "goodreads_url": "https://www.goodreads.com/search?utf8=%E2%9C%93&q=Jerry+Pournelle&search_type=books&search%5Bfield%5D=author"
    },
    {
      "id": "joan-d-vinge",
      "name": "Joan D. Vinge",
      "genre": "Science Fiction",
      "known_for": "The Snow Queen",
      "goodreads_url": "https://www.goodreads.com/search?utf8=%E2%9C%93&q=Joan+D.+Vinge&search_type=books&search%5Bfield%5D=author"
    },
    {
      "id": "joanna-russ",
      "name": "Joanna Russ",
      "genre": "Science Fiction",
      "known_for": "The Female Man",
      "goodreads_url": "https://www.goodreads.com/search?utf8=%E2%9C%93&q=Joanna+Russ&search_type=books&search%5Bfield%5D=author"
    },
    {
      "id": "joe-haldeman",
      "name": "Joe Haldeman",
      "genre": "Science Fiction",
      "known_for": "The Forever War",
      "goodreads_url": "https://www.goodreads.com/search?utf8=%E2%9C%93&q=Joe+Haldeman&search_type=books&search%5Bfield%5D=author"
    },
    {
      "id": "john-brunner",
      "name": "John Brunner",
      "genre": "Science Fiction",
      "known_for": "Stand on Zanzibar",
      "goodreads_url": "https://www.goodreads.com/search?utf8=%E2%9C%93&q=John+Brunner&search_type=books&search%5Bfield%5D=author"
    },
    {
      "id": "john-scalzi",
      "name": "John Scalzi",
      "genre": "Science Fiction",
      "known_for": "Old Man's War",
      "goodreads_url": "https://www.goodreads.com/search?utf8=%E2%9C%93&q=John+Scalzi&search_type=books&search%5Bfield%5D=author"
    },
    {
      "id": "john-varley",
      "name": "John Varley",
      "genre": "Science Fiction",
      "known_for": "The Ophiuchi Hotline; Steel Beach",
      "goodreads_url": "https://www.goodreads.com/search?utf8=%E2%9C%93&q=John+Varley&search_type=books&search%5Bfield%5D=author"
    },
    {
      "id": "john-wyndham",
      "name": "John Wyndham",
      "genre": "Science Fiction",
      "known_for": "The Day of the Triffids",
      "goodreads_url": "https://www.goodreads.com/search?utf8=%E2%9C%93&q=John+Wyndham&search_type=books&search%5Bfield%5D=author"
    },
    {
      "id": "judith-merril",
      "name": "Judith Merril",
      "genre": "Science Fiction",
      "known_for": "Shadow on the Hearth",
      "goodreads_url": "https://www.goodreads.com/search?utf8=%E2%9C%93&q=Judith+Merril&search_type=books&search%5Bfield%5D=author"
    },
    {
      "id": "jules-verne",
      "name": "Jules Verne",
      "genre": "Science Fiction",
      "known_for": "Twenty Thousand Leagues Under the Sea",
      "goodreads_url": "https://www.goodreads.com/search?utf8=%E2%9C%93&q=Jules+Verne&search_type=books&search%5Bfield%5D=author"
    },
    {
      "id": "kameron-hurley",
      "name": "Kameron Hurley",
      "genre": "Science Fiction",
      "known_for": "The Stars Are Legion; God's War",
      "goodreads_url": "https://www.goodreads.com/search?utf8=%E2%9C%93&q=Kameron+Hurley&search_type=books&search%5Bfield%5D=author"
    },
    {
      "id": "karl-schroeder",
      "name": "Karl Schroeder",
      "genre": "Science Fiction",
      "known_for": "Ventus; Lockstep",
      "goodreads_url": "https://www.goodreads.com/search?utf8=%E2%9C%93&q=Karl+Schroeder&search_type=books&search%5Bfield%5D=author"
    },
    {
      "id": "ken-liu",
      "name": "Ken Liu",
      "genre": "Science Fiction",
      "known_for": "The Paper Menagerie; The Dandelion Dynasty",
      "goodreads_url": "https://www.goodreads.com/search?utf8=%E2%9C%93&q=Ken+Liu&search_type=books&search%5Bfield%5D=author"
    },
    {
      "id": "ken-macleod",
      "name": "Ken MacLeod",
      "genre": "Science Fiction",
      "known_for": "The Fall Revolution",
      "goodreads_url": "https://www.goodreads.com/search?utf8=%E2%9C%93&q=Ken+MacLeod&search_type=books&search%5Bfield%5D=author"
    },
    {
      "id": "kim-stanley-robinson",
      "name": "Kim Stanley Robinson",
      "genre": "Science Fiction",
      "known_for": "Red Mars",
      "goodreads_url": "https://www.goodreads.com/search?utf8=%E2%9C%93&q=Kim+Stanley+Robinson&search_type=books&search%5Bfield%5D=author"
    },
    {
      "id": "kurt-vonnegut",
      "name": "Kurt Vonnegut",
      "genre": "Science Fiction",
      "known_for": "Slaughterhouse-Five; Cat's Cradle",
      "goodreads_url": "https://www.goodreads.com/search?utf8=%E2%9C%93&q=Kurt+Vonnegut&search_type=books&search%5Bfield%5D=author"
    },
    {
      "id": "larry-niven",
      "name": "Larry Niven",
      "genre": "Science Fiction",
      "known_for": "Ringworld",
      "goodreads_url": "https://www.goodreads.com/search?utf8=%E2%9C%93&q=Larry+Niven&search_type=books&search%5Bfield%5D=author"
    },
    {
      "id": "lauren-beukes",
      "name": "Lauren Beukes",
      "genre": "Science Fiction",
      "known_for": "Moxyland; The Shining Girls",
      "goodreads_url": "https://www.goodreads.com/search?utf8=%E2%9C%93&q=Lauren+Beukes&search_type=books&search%5Bfield%5D=author"
    },
    {
      "id": "leigh-brackett",
      "name": "Leigh Brackett",
      "genre": "Science Fiction",
      "known_for": "The Long Tomorrow; Eric John Stark",
      "goodreads_url": "https://www.goodreads.com/search?utf8=%E2%9C%93&q=Leigh+Brackett&search_type=books&search%5Bfield%5D=author"
    },
    {
      "id": "linda-nagata",
      "name": "Linda Nagata",
      "genre": "Science Fiction",
      "known_for": "The Bohr Maker; The Red",
      "goodreads_url": "https://www.goodreads.com/search?utf8=%E2%9C%93&q=Linda+Nagata&search_type=books&search%5Bfield%5D=author"
    },
    {
      "id": "liu-cixin",
      "name": "Liu Cixin",
      "genre": "Science Fiction",
      "known_for": "The Three-Body Problem",
      "goodreads_url": "https://www.goodreads.com/search?utf8=%E2%9C%93&q=Liu+Cixin&search_type=books&search%5Bfield%5D=author"
    },
    {
      "id": "lois-mcmaster-bujold",
      "name": "Lois McMaster Bujold",
      "genre": "Science Fiction",
      "known_for": "The Vorkosigan Saga",
      "goodreads_url": "https://www.goodreads.com/search?utf8=%E2%9C%93&q=Lois+McMaster+Bujold&search_type=books&search%5Bfield%5D=author"
    },
    {
      "id": "m-john-harrison",
      "name": "M. John Harrison",
      "genre": "Science Fiction",
      "known_for": "Light; Viriconium",
      "goodreads_url": "https://www.goodreads.com/search?utf8=%E2%9C%93&q=M.+John+Harrison&search_type=books&search%5Bfield%5D=author"
    },
    {
      "id": "margaret-atwood",
      "name": "Margaret Atwood",
      "genre": "Science Fiction",
      "known_for": "The Handmaid's Tale; Oryx and Crake",
      "goodreads_url": "https://www.goodreads.com/search?utf8=%E2%9C%93&q=Margaret+Atwood&search_type=books&search%5Bfield%5D=author"
    },
    {
      "id": "marion-zimmer-bradley",
      "name": "Marion Zimmer Bradley",
      "genre": "Science Fiction",
      "known_for": "Darkover",
      "goodreads_url": "https://www.goodreads.com/search?utf8=%E2%9C%93&q=Marion+Zimmer+Bradley&search_type=books&search%5Bfield%5D=author"
    },
    {
      "id": "martha-wells",
      "name": "Martha Wells",
      "genre": "Science Fiction",
      "known_for": "The Murderbot Diaries",
      "goodreads_url": "https://www.goodreads.com/search?utf8=%E2%9C%93&q=Martha+Wells&search_type=books&search%5Bfield%5D=author"
    },
    {
      "id": "mary-robinette-kowal",
      "name": "Mary Robinette Kowal",
      "genre": "Science Fiction",
      "known_for": "The Calculating Stars",
      "goodreads_url": "https://www.goodreads.com/search?utf8=%E2%9C%93&q=Mary+Robinette+Kowal&search_type=books&search%5Bfield%5D=author"
    },
    {
      "id": "maureen-f-mchugh",
      "name": "Maureen F. McHugh",
      "genre": "Science Fiction",
      "known_for": "China Mountain Zhang",
      "goodreads_url": "https://www.goodreads.com/search?utf8=%E2%9C%93&q=Maureen+F.+McHugh&search_type=books&search%5Bfield%5D=author"
    },
    {
      "id": "max-brooks",
      "name": "Max Brooks",
      "genre": "Science Fiction",
      "known_for": "World War Z",
      "goodreads_url": "https://www.goodreads.com/search?utf8=%E2%9C%93&q=Max+Brooks&search_type=books&search%5Bfield%5D=author"
    },
    {
      "id": "michael-crichton",
      "name": "Michael Crichton",
      "genre": "Science Fiction",
      "known_for": "Jurassic Park",
      "goodreads_url": "https://www.goodreads.com/search?utf8=%E2%9C%93&q=Michael+Crichton&search_type=books&search%5Bfield%5D=author"
    },
    {
      "id": "mike-resnick",
      "name": "Mike Resnick",
      "genre": "Science Fiction",
      "known_for": "Santiago; Kirinyaga",
      "goodreads_url": "https://www.goodreads.com/search?utf8=%E2%9C%93&q=Mike+Resnick&search_type=books&search%5Bfield%5D=author"
    },
    {
      "id": "mur-lafferty",
      "name": "Mur Lafferty",
      "genre": "Science Fiction",
      "known_for": "Six Wakes",
      "goodreads_url": "https://www.goodreads.com/search?utf8=%E2%9C%93&q=Mur+Lafferty&search_type=books&search%5Bfield%5D=author"
    },
    {
      "id": "murray-leinster",
      "name": "Murray Leinster",
      "genre": "Science Fiction",
      "known_for": "First Contact",
      "goodreads_url": "https://www.goodreads.com/search?utf8=%E2%9C%93&q=Murray+Leinster&search_type=books&search%5Bfield%5D=author"
    },
    {
      "id": "nancy-kress",
      "name": "Nancy Kress",
      "genre": "Science Fiction",
      "known_for": "Beggars in Spain",
      "goodreads_url": "https://www.goodreads.com/search?utf8=%E2%9C%93&q=Nancy+Kress&search_type=books&search%5Bfield%5D=author"
    },
    {
      "id": "neal-asher",
      "name": "Neal Asher",
      "genre": "Science Fiction",
      "known_for": "Gridlinked (Polity)",
      "goodreads_url": "https://www.goodreads.com/search?utf8=%E2%9C%93&q=Neal+Asher&search_type=books&search%5Bfield%5D=author"
    },
    {
      "id": "neal-stephenson",
      "name": "Neal Stephenson",
      "genre": "Science Fiction",
      "known_for": "Snow Crash; Cryptonomicon",
      "goodreads_url": "https://www.goodreads.com/search?utf8=%E2%9C%93&q=Neal+Stephenson&search_type=books&search%5Bfield%5D=author"
    },
    {
      "id": "nicola-griffith",
      "name": "Nicola Griffith",
      "genre": "Science Fiction",
      "known_for": "Ammonite; Slow River",
      "goodreads_url": "https://www.goodreads.com/search?utf8=%E2%9C%93&q=Nicola+Griffith&search_type=books&search%5Bfield%5D=author"
    },
    {
      "id": "nnedi-okorafor",
      "name": "Nnedi Okorafor",
      "genre": "Science Fiction",
      "known_for": "Binti; Who Fears Death",
      "goodreads_url": "https://www.goodreads.com/search?utf8=%E2%9C%93&q=Nnedi+Okorafor&search_type=books&search%5Bfield%5D=author"
    },
    {
      "id": "norman-spinrad",
      "name": "Norman Spinrad",
      "genre": "Science Fiction",
      "known_for": "Bug Jack Barron",
      "goodreads_url": "https://www.goodreads.com/search?utf8=%E2%9C%93&q=Norman+Spinrad&search_type=books&search%5Bfield%5D=author"
    },
    {
      "id": "octavia-e-butler",
      "name": "Octavia E. Butler",
      "genre": "Science Fiction",
      "known_for": "Kindred; Parable of the Sower",
      "goodreads_url": "https://www.goodreads.com/search?utf8=%E2%9C%93&q=Octavia+E.+Butler&search_type=books&search%5Bfield%5D=author"
    },
    {
      "id": "olaf-stapledon",
      "name": "Olaf Stapledon",
      "genre": "Science Fiction",
      "known_for": "Last and First Men; Star Maker",
      "goodreads_url": "https://www.goodreads.com/search?utf8=%E2%9C%93&q=Olaf+Stapledon&search_type=books&search%5Bfield%5D=author"
    },
    {
      "id": "orson-scott-card",
      "name": "Orson Scott Card",
      "genre": "Science Fiction",
      "known_for": "Ender's Game",
      "goodreads_url": "https://www.goodreads.com/search?utf8=%E2%9C%93&q=Orson+Scott+Card&search_type=books&search%5Bfield%5D=author"
    },
    {
      "id": "paolo-bacigalupi",
      "name": "Paolo Bacigalupi",
      "genre": "Science Fiction",
      "known_for": "The Windup Girl",
      "goodreads_url": "https://www.goodreads.com/search?utf8=%E2%9C%93&q=Paolo+Bacigalupi&search_type=books&search%5Bfield%5D=author"
    },
    {
      "id": "pat-cadigan",
      "name": "Pat Cadigan",
      "genre": "Science Fiction",
      "known_for": "Synners; Mindplayers",
      "goodreads_url": "https://www.goodreads.com/search?utf8=%E2%9C%93&q=Pat+Cadigan&search_type=books&search%5Bfield%5D=author"
    },
    {
      "id": "paul-mcauley",
      "name": "Paul McAuley",
      "genre": "Science Fiction",
      "known_for": "Fairyland; The Quiet War",
      "goodreads_url": "https://www.goodreads.com/search?utf8=%E2%9C%93&q=Paul+McAuley&search_type=books&search%5Bfield%5D=author"
    },
    {
      "id": "peter-f-hamilton",
      "name": "Peter F. Hamilton",
      "genre": "Science Fiction",
      "known_for": "Pandora's Star",
      "goodreads_url": "https://www.goodreads.com/search?utf8=%E2%9C%93&q=Peter+F.+Hamilton&search_type=books&search%5Bfield%5D=author"
    },
    {
      "id": "peter-watts",
      "name": "Peter Watts",
      "genre": "Science Fiction",
      "known_for": "Blindsight",
      "goodreads_url": "https://www.goodreads.com/search?utf8=%E2%9C%93&q=Peter+Watts&search_type=books&search%5Bfield%5D=author"
    },
    {
      "id": "philip-jose-farmer",
      "name": "Philip José Farmer",
      "genre": "Science Fiction",
      "known_for": "Riverworld",
      "goodreads_url": "https://www.goodreads.com/search?utf8=%E2%9C%93&q=Philip+Jos%C3%A9+Farmer&search_type=books&search%5Bfield%5D=author"
    },
    {
      "id": "philip-k-dick",
      "name": "Philip K. Dick",
      "genre": "Science Fiction",
      "known_for": "Do Androids Dream of Electric Sheep?; Ubik",
      "goodreads_url": "https://www.goodreads.com/search?utf8=%E2%9C%93&q=Philip+K.+Dick&search_type=books&search%5Bfield%5D=author"
    },
    {
      "id": "pierce-brown",
      "name": "Pierce Brown",
      "genre": "Science Fiction",
      "known_for": "Red Rising",
      "goodreads_url": "https://www.goodreads.com/search?utf8=%E2%9C%93&q=Pierce+Brown&search_type=books&search%5Bfield%5D=author"
    },
    {
      "id": "poul-anderson",
      "name": "Poul Anderson",
      "genre": "Science Fiction",
      "known_for": "Tau Zero; The High Crusade",
      "goodreads_url": "https://www.goodreads.com/search?utf8=%E2%9C%93&q=Poul+Anderson&search_type=books&search%5Bfield%5D=author"
    },
    {
      "id": "ray-bradbury",
      "name": "Ray Bradbury",
      "genre": "Science Fiction",
      "known_for": "Fahrenheit 451; The Martian Chronicles",
      "goodreads_url": "https://www.goodreads.com/search?utf8=%E2%9C%93&q=Ray+Bradbury&search_type=books&search%5Bfield%5D=author"
    },
    {
      "id": "richard-k-morgan",
      "name": "Richard K. Morgan",
      "genre": "Science Fiction",
      "known_for": "Altered Carbon",
      "goodreads_url": "https://www.goodreads.com/search?utf8=%E2%9C%93&q=Richard+K.+Morgan&search_type=books&search%5Bfield%5D=author"
    },
    {
      "id": "rivers-solomon",
      "name": "Rivers Solomon",
      "genre": "Science Fiction",
      "known_for": "An Unkindness of Ghosts",
      "goodreads_url": "https://www.goodreads.com/search?utf8=%E2%9C%93&q=Rivers+Solomon&search_type=books&search%5Bfield%5D=author"
    },
    {
      "id": "robert-a-heinlein",
      "name": "Robert A. Heinlein",
      "genre": "Science Fiction",
      "known_for": "Stranger in a Strange Land; Starship Troopers",
      "goodreads_url": "https://www.goodreads.com/search?utf8=%E2%9C%93&q=Robert+A.+Heinlein&search_type=books&search%5Bfield%5D=author"
    },
    {
      "id": "robert-charles-wilson",
      "name": "Robert Charles Wilson",
      "genre": "Science Fiction",
      "known_for": "Spin",
      "goodreads_url": "https://www.goodreads.com/search?utf8=%E2%9C%93&q=Robert+Charles+Wilson&search_type=books&search%5Bfield%5D=author"
    },
    {
      "id": "robert-j-sawyer",
      "name": "Robert J. Sawyer",
      "genre": "Science Fiction",
      "known_for": "Hominids; The WWW Trilogy",
      "goodreads_url": "https://www.goodreads.com/search?utf8=%E2%9C%93&q=Robert+J.+Sawyer&search_type=books&search%5Bfield%5D=author"
    },
    {
      "id": "robert-reed",
      "name": "Robert Reed",
      "genre": "Science Fiction",
      "known_for": "Marrow; The Great Ship",
      "goodreads_url": "https://www.goodreads.com/search?utf8=%E2%9C%93&q=Robert+Reed&search_type=books&search%5Bfield%5D=author"
    },
    {
      "id": "robert-silverberg",
      "name": "Robert Silverberg",
      "genre": "Science Fiction",
      "known_for": "Dying Inside; Lord Valentine's Castle",
      "goodreads_url": "https://www.goodreads.com/search?utf8=%E2%9C%93&q=Robert+Silverberg&search_type=books&search%5Bfield%5D=author"
    },
    {
      "id": "s-m-stirling",
      "name": "S.M. Stirling",
      "genre": "Science Fiction",
      "known_for": "Dies the Fire (Emberverse)",
      "goodreads_url": "https://www.goodreads.com/search?utf8=%E2%9C%93&q=S.M.+Stirling&search_type=books&search%5Bfield%5D=author"
    },
    {
      "id": "samuel-r-delany",
      "name": "Samuel R. Delany",
      "genre": "Science Fiction",
      "known_for": "Dhalgren; Babel-17",
      "goodreads_url": "https://www.goodreads.com/search?utf8=%E2%9C%93&q=Samuel+R.+Delany&search_type=books&search%5Bfield%5D=author"
    },
    {
      "id": "sheri-s-tepper",
      "name": "Sheri S. Tepper",
      "genre": "Science Fiction",
      "known_for": "Grass; The Gate to Women's Country",
      "goodreads_url": "https://www.goodreads.com/search?utf8=%E2%9C%93&q=Sheri+S.+Tepper&search_type=books&search%5Bfield%5D=author"
    },
    {
      "id": "stanisaw-lem",
      "name": "Stanisław Lem",
      "genre": "Science Fiction",
      "known_for": "Solaris",
      "goodreads_url": "https://www.goodreads.com/search?utf8=%E2%9C%93&q=Stanis%C5%82aw+Lem&search_type=books&search%5Bfield%5D=author"
    },
    {
      "id": "stephen-baxter",
      "name": "Stephen Baxter",
      "genre": "Science Fiction",
      "known_for": "The Xeelee Sequence",
      "goodreads_url": "https://www.goodreads.com/search?utf8=%E2%9C%93&q=Stephen+Baxter&search_type=books&search%5Bfield%5D=author"
    },
    {
      "id": "sue-burke",
      "name": "Sue Burke",
      "genre": "Science Fiction",
      "known_for": "Semiosis",
      "goodreads_url": "https://www.goodreads.com/search?utf8=%E2%9C%93&q=Sue+Burke&search_type=books&search%5Bfield%5D=author"
    },
    {
      "id": "suzanne-collins",
      "name": "Suzanne Collins",
      "genre": "Science Fiction",
      "known_for": "The Hunger Games",
      "goodreads_url": "https://www.goodreads.com/search?utf8=%E2%9C%93&q=Suzanne+Collins&search_type=books&search%5Bfield%5D=author"
    },
    {
      "id": "sylvain-neuvel",
      "name": "Sylvain Neuvel",
      "genre": "Science Fiction",
      "known_for": "Sleeping Giants",
      "goodreads_url": "https://www.goodreads.com/search?utf8=%E2%9C%93&q=Sylvain+Neuvel&search_type=books&search%5Bfield%5D=author"
    },
    {
      "id": "tade-thompson",
      "name": "Tade Thompson",
      "genre": "Science Fiction",
      "known_for": "Rosewater",
      "goodreads_url": "https://www.goodreads.com/search?utf8=%E2%9C%93&q=Tade+Thompson&search_type=books&search%5Bfield%5D=author"
    },
    {
      "id": "tamsyn-muir",
      "name": "Tamsyn Muir",
      "genre": "Science Fiction",
      "known_for": "Gideon the Ninth",
      "goodreads_url": "https://www.goodreads.com/search?utf8=%E2%9C%93&q=Tamsyn+Muir&search_type=books&search%5Bfield%5D=author"
    },
    {
      "id": "ted-chiang",
      "name": "Ted Chiang",
      "genre": "Science Fiction",
      "known_for": "Stories of Your Life and Others",
      "goodreads_url": "https://www.goodreads.com/search?utf8=%E2%9C%93&q=Ted+Chiang&search_type=books&search%5Bfield%5D=author"
    },
    {
      "id": "theodore-sturgeon",
      "name": "Theodore Sturgeon",
      "genre": "Science Fiction",
      "known_for": "More Than Human",
      "goodreads_url": "https://www.goodreads.com/search?utf8=%E2%9C%93&q=Theodore+Sturgeon&search_type=books&search%5Bfield%5D=author"
    },
    {
      "id": "timothy-zahn",
      "name": "Timothy Zahn",
      "genre": "Science Fiction",
      "known_for": "Thrawn (Heir to the Empire)",
      "goodreads_url": "https://www.goodreads.com/search?utf8=%E2%9C%93&q=Timothy+Zahn&search_type=books&search%5Bfield%5D=author"
    },
    {
      "id": "tochi-onyebuchi",
      "name": "Tochi Onyebuchi",
      "genre": "Science Fiction",
      "known_for": "Riot Baby",
      "goodreads_url": "https://www.goodreads.com/search?utf8=%E2%9C%93&q=Tochi+Onyebuchi&search_type=books&search%5Bfield%5D=author"
    },
    {
      "id": "ursula-k-le-guin",
      "name": "Ursula K. Le Guin",
      "genre": "Science Fiction",
      "known_for": "The Left Hand of Darkness; The Dispossessed",
      "goodreads_url": "https://www.goodreads.com/search?utf8=%E2%9C%93&q=Ursula+K.+Le+Guin&search_type=books&search%5Bfield%5D=author"
    },
    {
      "id": "vernor-vinge",
      "name": "Vernor Vinge",
      "genre": "Science Fiction",
      "known_for": "A Fire Upon the Deep",
      "goodreads_url": "https://www.goodreads.com/search?utf8=%E2%9C%93&q=Vernor+Vinge&search_type=books&search%5Bfield%5D=author"
    },
    {
      "id": "veronica-roth",
      "name": "Veronica Roth",
      "genre": "Science Fiction",
      "known_for": "Divergent",
      "goodreads_url": "https://www.goodreads.com/search?utf8=%E2%9C%93&q=Veronica+Roth&search_type=books&search%5Bfield%5D=author"
    },
    {
      "id": "vonda-n-mcintyre",
      "name": "Vonda N. McIntyre",
      "genre": "Science Fiction",
      "known_for": "Dreamsnake",
      "goodreads_url": "https://www.goodreads.com/search?utf8=%E2%9C%93&q=Vonda+N.+McIntyre&search_type=books&search%5Bfield%5D=author"
    },
    {
      "id": "walter-jon-williams",
      "name": "Walter Jon Williams",
      "genre": "Science Fiction",
      "known_for": "Hardwired; Dread Empire's Fall",
      "goodreads_url": "https://www.goodreads.com/search?utf8=%E2%9C%93&q=Walter+Jon+Williams&search_type=books&search%5Bfield%5D=author"
    },
    {
      "id": "walter-m-miller-jr",
      "name": "Walter M. Miller Jr.",
      "genre": "Science Fiction",
      "known_for": "A Canticle for Leibowitz",
      "goodreads_url": "https://www.goodreads.com/search?utf8=%E2%9C%93&q=Walter+M.+Miller+Jr.&search_type=books&search%5Bfield%5D=author"
    },
    {
      "id": "william-gibson",
      "name": "William Gibson",
      "genre": "Science Fiction",
      "known_for": "Neuromancer",
      "goodreads_url": "https://www.goodreads.com/search?utf8=%E2%9C%93&q=William+Gibson&search_type=books&search%5Bfield%5D=author"
    },
    {
      "id": "yoon-ha-lee",
      "name": "Yoon Ha Lee",
      "genre": "Science Fiction",
      "known_for": "Ninefox Gambit",
      "goodreads_url": "https://www.goodreads.com/search?utf8=%E2%9C%93&q=Yoon+Ha+Lee&search_type=books&search%5Bfield%5D=author"
    }
  ]
}